[
  {
    "id": "ev-2802",
    "date": "2026-02-28",
    "actor": "us_israel",
    "title": "War Outbreak: Preemptive Strikes",
    "desc": "US and Israel launch strikes on Iranian military and air defenses in Tehran and Isfahan.",
    "priceBrent": 71.32,
    "priceTTF": 28.40,
    "lat": 35.68,
    "lng": 51.38,
    "sourceUrl": "https://www.reuters.com/world/middle-east/",
    "sourceLabel": "Reuters"
  },
  {
    "id": "ev-0103",
    "date": "2026-03-01",
    "actor": "iran",
    "title": "Iranian Retaliation Against UAE",
    "desc": "Swarm attack on Jebel Ali Port. Tanker Athe Nova struck.",
    "priceBrent": null,
    "priceTTF": null,
    "lat": 25.00,
    "lng": 55.05,
    "sourceUrl": "https://www.aljazeera.com/tag/iran/",
    "sourceLabel": "Al Jazeera"
  },
  {
    "id": "ev-0203",
    "date": "2026-03-02",
    "actor": "iran",
    "title": "Ras Tanura & Stena Imperative",
    "desc": "Attack on Saudi Arabia's largest refinery.",
    "priceBrent": 77.24,
    "priceTTF": 31.50,
    "targetId": "ras-tanura",
    "sourceUrl": "https://www.reuters.com/business/energy/",
    "sourceLabel": "Reuters Energy"
  },
  {
    "id": "ev-0303",
    "date": "2026-03-03",
    "actor": "iran",
    "title": "Fujairah Bypass Neutralized",
    "desc": "Repeated attacks cripple UAE's Fujairah port.",
    "priceBrent": 88.59,
    "priceTTF": 34.20,
    "targetId": "fujairah",
    "sourceUrl": "https://www.reuters.com/business/energy/",
    "sourceLabel": "Reuters Energy"
  },
  {
    "id": "ev-0703",
    "date": "2026-03-07",
    "actor": "us_israel",
    "title": "IDF Dismantles Iranian Logistics",
    "desc": "Abadan refinery and oil depots critically damaged.",
    "priceBrent": 95.74,
    "priceTTF": 39.80,
    "targetId": "abadan",
    "sourceUrl": "https://www.timesofisrael.com/",
    "sourceLabel": "Times of Israel"
  },
  {
    "id": "ev-0903",
    "date": "2026-03-09",
    "actor": "iran",
    "title": "Bapco Sitra Hit",
    "desc": "Iranian drones strike Bahrain's primary refinery.",
    "priceBrent": 94.35,
    "priceTTF": 38.50,
    "targetId": "bapco",
    "sourceUrl": "https://www.aljazeera.com/tag/bahrain/",
    "sourceLabel": "Al Jazeera"
  },
  {
    "id": "ev-1003",
    "date": "2026-03-10",
    "actor": "iran",
    "title": "Ruwais Refinery Shutdown",
    "desc": "Full shutdown of ADNOC's complex.",
    "priceBrent": 89.84,
    "priceTTF": 41.00,
    "targetId": "ruwais",
    "sourceUrl": "https://www.reuters.com/business/energy/",
    "sourceLabel": "Reuters Energy"
  },
  {
    "id": "ev-1203",
    "date": "2026-03-12",
    "actor": "iran",
    "title": "Majnoon & Marine Engagements",
    "desc": "Iraq drawn in. CENTCOM sinks over 60 vessels.",
    "priceBrent": 102.38,
    "priceTTF": 48.50,
    "targetId": "majnoon",
    "sourceUrl": "https://www.centcom.mil/MEDIA/PRESS-RELEASES/",
    "sourceLabel": "CENTCOM"
  },
  {
    "id": "ev-1303",
    "date": "2026-03-13",
    "actor": "us_israel",
    "title": "Kharg Island Ultimatum",
    "desc": "Massive US bombing of Kharg Island logistics.",
    "priceBrent": 103.23,
    "priceTTF": 52.10,
    "targetId": "kharg",
    "sourceUrl": "https://www.reuters.com/world/middle-east/",
    "sourceLabel": "Reuters"
  },
  {
    "id": "ev-1603",
    "date": "2026-03-16",
    "actor": "iran",
    "title": "Shah Sour Gas Field Attacked",
    "desc": "Removes 5% of world sulfur from the market.",
    "priceBrent": 101.04,
    "priceTTF": 65.40,
    "targetId": "shah",
    "sourceUrl": "https://www.reuters.com/business/energy/",
    "sourceLabel": "Reuters Energy"
  },
  {
    "id": "ev-1803",
    "date": "2026-03-18",
    "actor": "us_israel",
    "title": "Rubicon: South Pars Bombed",
    "desc": "Israel bombs Iran's primary gas source.",
    "priceBrent": 108.50,
    "priceTTF": 89.00,
    "targetId": "south-pars",
    "sourceUrl": "https://www.timesofisrael.com/",
    "sourceLabel": "Times of Israel"
  },
  {
    "id": "ev-1903",
    "date": "2026-03-19",
    "actor": "iran",
    "title": "LNG Shock & Kuwait Attack",
    "desc": "Fires at Ras Laffan (Qatar). Kuwaiti refineries bombed.",
    "priceBrent": 113.26,
    "priceTTF": 145.50,
    "targetId": "ras-laffan",
    "sourceUrl": "https://www.aljazeera.com/tag/qatar/",
    "sourceLabel": "Al Jazeera"
  }
]
